eka_mcp_server/__init__.py
eka_mcp_server/constants.py
eka_mcp_server/eka_client.py
eka_mcp_server/mcp_server.py
eka_mcp_server/models.py
eka_mcp_server/server.py
eka_mcp_server/utils.py
eka_mcp_server-0.3.2.dist-info/METADATA
eka_mcp_server-0.3.2.dist-info/WHEEL
eka_mcp_server-0.3.2.dist-info/entry_points.txt
eka_mcp_server-0.3.2.dist-info/licenses/LICENSE
eka_mcp_server-0.3.2.dist-info/RECORD
